langchain_pymupdf4llm/__init__.py
langchain_pymupdf4llm/pymupdf4llm_loader.py
langchain_pymupdf4llm/pymupdf4llm_parser.py
langchain_pymupdf4llm-0.5.0.dist-info/METADATA
langchain_pymupdf4llm-0.5.0.dist-info/WHEEL
langchain_pymupdf4llm-0.5.0.dist-info/licenses/LICENSE
langchain_pymupdf4llm-0.5.0.dist-info/RECORD
