Metadata-Version: 2.4
Name: langchain-pymupdf4llm
Version: 0.5.0
Summary: An integration package connecting PyMuPDF4LLM to LangChain
License-Expression: MIT
License-File: LICENSE
Author: Lakindu Boteju
Author-email: lakinduboteju@gmail.com
Requires-Python: <4.0,>=3.11
Classifier: Programming Language :: Python :: 3
Classifier: Programming Language :: Python :: 3.11
Classifier: Programming Language :: Python :: 3.12
Classifier: Programming Language :: Python :: 3.13
Classifier: Programming Language :: Python :: 3.14
Requires-Dist: langchain-core (>=1.0.0,<2.0.0)
Requires-Dist: pymupdf4llm (>=0.1.0,<0.2.0)
Project-URL: Repository, https://github.com/lakinduboteju/langchain-pymupdf4llm
